sorsa/__init__.py
sorsa/config.py
sorsa/layer.py
sorsa/model.py
sorsa/trainer.py
sorsa-1.0.1.dist-info/METADATA
sorsa-1.0.1.dist-info/WHEEL
sorsa-1.0.1.dist-info/top_level.txt
sorsa-1.0.1.dist-info/RECORD
