Metadata-Version: 2.1
Name: sorsa
Version: 1.0.1
Summary: "SORSA: Singular Values and Orthonormal Regularized Singular Vectors Adaptation of Large Language Models" implementation intergrated with Hugging Face transformers
Author-email: Yang Cao <gunale0926@hotmail.com>
Project-URL: Homepage, https://github.com/Gunale0926/SORSA/
Project-URL: Issues, https://github.com/Gunale0926/SORSA/issues
Classifier: Programming Language :: Python :: 3
Classifier: License :: OSI Approved :: Apache Software License
Classifier: Operating System :: OS Independent
Requires-Python: >=3.8
Requires-Dist: torch >=1.8.0
Requires-Dist: transformers >=4.42.0
